processPLS/__init__.py
processPLS/data.py
processPLS/datasets.py
processPLS/model.py
processPLS/data/OilDistillationData.csv
processPLS/data/ValdeLoirData.csv
processPLS/data/__init__.py
ProcessPLS-1.7.dist-info/LICENSE
ProcessPLS-1.7.dist-info/METADATA
ProcessPLS-1.7.dist-info/WHEEL
ProcessPLS-1.7.dist-info/top_level.txt
ProcessPLS-1.7.dist-info/RECORD
