Metadata-Version: 2.1
Name: ProcessPLS
Version: 1.7
Summary: Implementation of ProcessPLS in Python
Home-page: UNKNOWN
Author: Sin Yong Teng
Author-email: tsyet12@gmail.com
License: BSD 2-Clause
Keywords: Path Modelling,Chemometrics,Process Analytical Technology,Machine Learning
Platform: UNKNOWN
Classifier: Development Status :: 4 - Beta
Classifier: Intended Audience :: Developers
Classifier: Topic :: Software Development :: Build Tools
Classifier: License :: OSI Approved :: BSD License
Classifier: Programming Language :: Python :: 3
Classifier: Programming Language :: Python :: 3.4
Classifier: Programming Language :: Python :: 3.5
Classifier: Programming Language :: Python :: 3.6
Requires-Dist: numpy
Requires-Dist: matplotlib
Requires-Dist: sklearn
Requires-Dist: networkx
Requires-Dist: pandas
